{
    "0xB8AF3137": {
        "name": "HAS_VEHICLE_BEEN_DAMAGED_BY_BULLETS",
        "params": [
            {
                "name": "vehicle",
                "type": "Vehicle",
                "description": "The target vehicle."
            }
        ],
        "return_type": "BOOL",
        "description": "",
        "examples": [],
        "hash": "0xB8AF3137",
        "ns": "CFX",
        "apiset": "server",
        "resultsDescription": "Returns whether or not the target vehicle has been damaged by bullets."
    }
}