{
    "0x3DDEB0E6": {
        "name": "TASK_PLAY_ANIM_ADVANCED",
        "params": [
            {
                "name": "ped",
                "type": "Ped",
                "description": "The ped you want to play the animation"
            },
            {
                "name": "animDictionary",
                "type": "const char*",
                "description": "The animation dictionary"
            },
            {
                "name": "animationName",
                "type": "const char*",
                "description": "The animation name"
            },
            {
                "name": "posX",
                "type": "float",
                "description": "Initial X position of the task"
            },
            {
                "name": "posY",
                "type": "float",
                "description": "Initial Y position of the task"
            },
            {
                "name": "posZ",
                "type": "float",
                "description": "Initial Z position of the task"
            },
            {
                "name": "rotX",
                "type": "float",
                "description": "Initial X rotation of the task"
            },
            {
                "name": "rotY",
                "type": "float",
                "description": "Initial Y rotation of the task"
            },
            {
                "name": "rotZ",
                "type": "float",
                "description": "Initial Z rotation of the task"
            },
            {
                "name": "blendInSpeed",
                "type": "float",
                "description": "The speed at which the animation blends in. Lower is slower and higher is faster, 1.0 is normal, 8.0 is basically instant"
            },
            {
                "name": "blendOutSpeed",
                "type": "float",
                "description": "The speed at which the animation blends out. Lower is slower and higher is faster, 1.0 is normal, 8.0 is basically instant"
            },
            {
                "name": "duration",
                "type": "int",
                "description": "The duration of the animation in milliseconds. -1 will play the animation until canceled"
            },
            {
                "name": "flag",
                "type": "Any",
                "description": "See [`TASK_PLAY_ANIM`](#\\_0xEA47FE3719165B94)"
            },
            {
                "name": "animTime",
                "type": "float",
                "description": "Value between 0.0 and 1.0, lets you start an animation from the given point"
            },
            {
                "name": "p14",
                "type": "Any"
            },
            {
                "name": "p15",
                "type": "Any"
            }
        ],
        "return_type": "void",
        "description": "Similar in functionality to [`TASK_PLAY_ANIM`](#\\_0xEA47FE3719165B94), except the position and rotation parameters let you specify the initial position and rotation of the task. The ped is teleported to the position specified.\r\n[Animations list](https://alexguirre.github.io/animations-list/)\n\n**This is the server-side RPC native equivalent of the client native [TASK_PLAY_ANIM_ADVANCED](?\\_0x83CDB10EA29B370B).**",
        "examples": [],
        "hash": "0x3DDEB0E6",
        "ns": "CFX",
        "apiset": "server"
    }
}